<annotation verified="yes">
                                    <folder>Annotation</folder>
                                    <filename>erodouga_20sec 2_frame_84</filename>
                                    <path>/Users/nf/Downloads/erodouga_20sec 2_output/JPEGImages/erodouga_20sec 2_frame_84.jpg</path>
                                    <source>
                                        <database>Unknown</database>
                                    </source>
                                    <size>
                                        <width>1280</width>
                                        <height>720</height>
                                        <depth>3</depth>
                                    </size>
                                    <segmented>0</segmented>
                                    <object>
                                            <name>pennis</name>
                                            <pose>Unspecified</pose>
                                            <truncated>0</truncated>
                                            <difficult>0</difficult>
                                            <bndbox>
                                                <xmin>575.8419958419959</xmin>
                                                <ymin>144.91164241164242</ymin>
                                                <xmax>912.448024948025</xmax>
                                                <ymax>581.9178794178795</ymax>
                                            </bndbox>
                                    </object>
                                    </annotation>